gamesave/__init__.py
gamesave-1.0.1.dist-info/METADATA
gamesave-1.0.1.dist-info/WHEEL
gamesave-1.0.1.dist-info/licenses/LICENCE
gamesave-1.0.1.dist-info/RECORD
