Metadata-Version: 2.1
Name: gamesave
Version: 1.0.1
Summary: a small module to make hobbyist game development easier
Author-email: Sleepy82 <shgj7y1z@duck.com>
License-File: LICENCE
Classifier: License :: OSI Approved :: MIT License
Classifier: Operating System :: OS Independent
Classifier: Programming Language :: Python :: 3
Requires-Python: >=3.7
